pit.py
pit-0.5.dist-info/WHEEL
pit-0.5.dist-info/top_level.txt
pit-0.5.dist-info/RECORD
pit-0.5.dist-info/METADATA
pit-0.5.dist-info/metadata.json
pit-0.5.dist-info/DESCRIPTION.rst
