Metadata-Version: 1.0
Name: pit
Version: 0.5
Summary: pit: account management tool
Home-page: UNKNOWN
Author: Yoshiori SHOJI
Author-email: yoshiori@gmail.com
License: UNKNOWN
Platform: UNKNOWN
